QueryHash/__init__.py
QueryHash/asgi.py
QueryHash/settings.py
QueryHash/urls.py
QueryHash/wsgi.py
myapp/__init__.py
myapp/admin.py
myapp/apps.py
myapp/middleware.py
myapp/models.py
myapp/tests.py
myapp/urls.py
myapp/views.py
myapp/migrations/0001_initial.py
myapp/migrations/__init__.py
QueryHash-0.1.0.dist-info/LICENSE
QueryHash-0.1.0.dist-info/METADATA
QueryHash-0.1.0.dist-info/WHEEL
QueryHash-0.1.0.dist-info/top_level.txt
QueryHash-0.1.0.dist-info/RECORD
